{
  "events": [
    {
      "id": 1,
      "title": "Maratón de Santiago 2025",
      "date": "2025-04-15",
      "location": "Santiago, Chile",
      "category": "running",
      "image": "/assets/images/events/maraton-santiago.jpg",
      "participants": 5000,
      "linkType": "internal",
      "link": "/results/maraton-santiago-2025.html"
    },
    {
      "id": 2,
      "title": "Ironman Pucón 2025",
      "date": "2025-02-22",
      "location": "Pucón, Chile",
      "category": "triatlon",
      "image": "/assets/images/events/ironman-pucon.jpg",
      "participants": 1200,
      "linkType": "external",
      "link": "https://resultados.ironman.com/2025/pucon"
    },
    {
      "id": 3,
      "title": "Desafío del Desierto",
      "date": "2025-05-10",
      "location": "San Pedro de Atacama",
      "category": "trail",
      "image": "/assets/images/events/trail-atacama.jpg",
      "participants": 800,
      "linkType": "internal",
      "link": "/results/trail-atacama-2025.html"
    },
    {
      "id": 4,
      "title": "Gran Fondo Valparaíso",
      "date": "2025-03-20",
      "location": "Valparaíso, Chile",
      "category": "ciclismo",
      "image": "/assets/images/events/ciclismo-valpo.jpg",
      "participants": 2500,
      "linkType": "external",
      "link": "https://granfondo.cl/resultados"
    },
    {
      "id": 5,
      "title": "Corrida de las Empresas",
      "date": "2025-06-05",
      "location": "Las Condes, Santiago",
      "category": "running",
      "image": "/assets/images/events/corrida-empresas.jpg",
      "participants": 3000,
      "linkType": "internal",
      "link": "/results/corrida-empresas-2025.html"
    },
    {
      "id": 6,
      "title": "Challenge La Serena",
      "date": "2025-01-28",
      "location": "La Serena, Chile",
      "category": "triatlon",
      "image": "/assets/images/events/challenge-serena.jpg",
      "participants": 900,
      "linkType": "external",
      "link": "https://challenge-family.com/results/laserena"
    }
  ]
}

